wxinghe/__init__.py
wxinghe/__main__.py
wxinghe/data_query.py
wxinghe-0.1.0.dist-info/METADATA
wxinghe-0.1.0.dist-info/WHEEL
wxinghe-0.1.0.dist-info/entry_points.txt
wxinghe-0.1.0.dist-info/RECORD
