Metadata-Version: 2.4
Name: wxinghe
Version: 0.1.0
Summary: 五八星河api
Author-email: 王梦迪 <wangmengdi06@58.com>
Requires-Python: >=3.10
Requires-Dist: jsonargparse>=4.40.1
Requires-Dist: polars>=1.32.0
Requires-Dist: pydantic>=2.11.7
Requires-Dist: requests>=2.32.4
